<dayTraderConfig>

	<version>V.11.26.0</version>

	<!-- Production account -->
	<!-- <accountCode>U1235379</accountCode> -->
	<!-- Paper trader account -->
  <accountCode>DU171047</accountCode>

	<!-- Trading configuration parameters -->
	<minTradeVolume>10000</minTradeVolume>
	<minBuyPrice>.50</minBuyPrice>
	<maxBuyPositions>5</maxBuyPositions>
	<maxBuyAmount>10000</maxBuyAmount>
	<minAccountBalance>25000</minAccountBalance>

  <databaseName>dayTrader_test</databaseName>
	<databaseUser>root</databaseUser>
	<databasePassword>r00t</databasePassword>

	<!-- Logging config params -->
	<dtLogFileName>/home/nathan/temp/dayTrader_test.log</dtLogFileName>
	<dtReportDirPath>/home/nathan/temp/Reports</dtReportDirPath>

	<!-- Timing config params -->
	<minutesBeforeCloseToBuy>600</minutesBeforeCloseToBuy>
	<rtScanIntervalMinutes>5</rtScanIntervalMinutes>

	<!-- Debug config params -->
	<useIB>TRUE</useIB>
	<useTD>TRUE</useTD>
	<ignoreMarketClosed>TRUE</ignoreMarketClosed>
	<useSimulateDate></useSimulateDate>
	<takeSnapshot>TRUE</takeSnapshot>
	<getRTData>TRUE</getRTData>
	<useSystemTime>TRUE</useSystemTime>


</dayTraderConfig>
